ipa_tool/__init__.py
ipa_tool/__main__.py
ipa_tool/analyze_macho.py
ipa_tool/calc_md5.py
ipa_tool/create_infos.py
ipa_tool/format_plist.py
ipa_tool/get_icon.py
ipa_tool/get_size.py
ipa_tool/load_ipa.py
ipa_tool/main.py
ipa_tool-1.5.0.dist-info/METADATA
ipa_tool-1.5.0.dist-info/WHEEL
ipa_tool-1.5.0.dist-info/entry_points.txt
ipa_tool-1.5.0.dist-info/RECORD
