Metadata-Version: 2.1
Name: ipa-tool
Version: 1.5.0
Summary: Simple tool for getting infos from Apple ipa archive
Author: DrEgg
Author-email: dev@dregg.me
Requires-Python: >=3.7.9,<4.0.0
Classifier: Programming Language :: Python :: 3
Classifier: Programming Language :: Python :: 3.8
Classifier: Programming Language :: Python :: 3.9
Classifier: Programming Language :: Python :: 3.10
Classifier: Programming Language :: Python :: 3.11
Classifier: Programming Language :: Python :: 3.12
Requires-Dist: lief (>=0.12.3,<0.13.0)
Requires-Dist: rich (>=12.6.0,<13.0.0)
Requires-Dist: typer (>=0.6.1,<0.7.0)
